[
  {
    "Name": "User 1",
    "Email": "user1@mail.com",
    "Phone": "111222333",
    "GithubLink": "github.user1.com",
    "StopwatchTime": "00:00:02"
  },
  {
    "Name": "User 2",
    "Email": "user2@mail.com",
    "Phone": "111222333",
    "GithubLink": "github.user2.com",
    "StopwatchTime": "00:00:04"
  },
  {
    "Name": "User 3",
    "Email": "user3@mail.com",
    "Phone": "111222333",
    "GithubLink": "github.user3.com",
    "StopwatchTime": "00:00:07"
  },
  {
    "Name": "User 4",
    "Email": "user4@mail.com",
    "Phone": "111222333",
    "GithubLink": "github.user4.com",
    "StopwatchTime": "00:00:08"
  },
  {
    "Name": "User 5",
    "Email": "user5@mail.com",
    "Phone": "111222333",
    "GithubLink": "github.user5.com",
    "StopwatchTime": "00:00:01"
  },
  {
    "Name": "User 6",
    "Email": "user6@mail.com",
    "Phone": "111222333",
    "GithubLink": "github.user6.com",
    "StopwatchTime": "00:00:05"
  }
]